[{"id":1,"first_name":"Mavra","last_name":"Warn","email":"mwarn0@baidu.com"},
{"id":2,"first_name":"Gwyn","last_name":"Mathiasen","email":"gmathiasen1@1688.com"},
{"id":3,"first_name":"Whittaker","last_name":"Extill","email":"wextill2@godaddy.com"},
{"id":4,"first_name":"Paulita","last_name":"Klees","email":"pklees3@live.com"},
{"id":5,"first_name":"Christiana","last_name":"Durtnall","email":"cdurtnall4@miibeian.gov.cn"},
{"id":6,"first_name":"Granger","last_name":"Basler","email":"gbasler5@i2i.jp"},
{"id":7,"first_name":"Fletcher","last_name":"Estoile","email":"festoile6@purevolume.com"},
{"id":8,"first_name":"Stevy","last_name":"Blamphin","email":"sblamphin7@tmall.com"},
{"id":9,"first_name":"Annabella","last_name":"Mott","email":"amott8@technorati.com"},
{"id":10,"first_name":"Camila","last_name":"Jereatt","email":"cjereatt9@oakley.com"},
{"id":11,"first_name":"Raquel","last_name":"Redmond","email":"rredmonda@dion.ne.jp"},
{"id":12,"first_name":"Gilberte","last_name":"Akehurst","email":"gakehurstb@google.nl"},
{"id":13,"first_name":"Lotti","last_name":"Pressnell","email":"lpressnellc@slate.com"},
{"id":14,"first_name":"Gerome","last_name":"Ambroise","email":"gambroised@quantcast.com"},
{"id":15,"first_name":"Mattie","last_name":"Wilhelmy","email":"mwilhelmye@themeforest.net"},
{"id":16,"first_name":"Cy","last_name":"Cleeve","email":"ccleevef@elpais.com"},
{"id":17,"first_name":"Chalmers","last_name":"Hinstock","email":"chinstockg@deliciousdays.com"},
{"id":18,"first_name":"Arlena","last_name":"Arnaldo","email":"aarnaldoh@oaic.gov.au"},
{"id":19,"first_name":"Alexandros","last_name":"Goldthorp","email":"agoldthorpi@census.gov"},
{"id":20,"first_name":"Kelvin","last_name":"Mahy","email":"kmahyj@webmd.com"},
{"id":21,"first_name":"Bernadine","last_name":"Brunsdon","email":"bbrunsdonk@google.com.hk"},
{"id":22,"first_name":"Allistir","last_name":"Spearing","email":"aspearingl@cnn.com"},
{"id":23,"first_name":"Ely","last_name":"Brushneen","email":"ebrushneenm@mit.edu"},
{"id":24,"first_name":"Halli","last_name":"Dilland","email":"hdillandn@webs.com"},
{"id":25,"first_name":"Austin","last_name":"Malley","email":"amalleyo@sohu.com"}]